{
  "820744140": {
    "username": "actually_yeah",
    "liked": [
      1490139089449865217
    ],
    "created_at": 1347503322.0,
    "verified": false
  },
  "2923365757": {
    "username": "BGhimself",
    "liked": [
      1490139089449865217
    ],
    "created_at": 1418092069.0,
    "verified": false,
    "location": "Manhattan Beach, paradise "
  },
  "1298753163764404224": {
    "username": "scorvorite",
    "liked": [
      1490228075933671429
    ],
    "created_at": 1598481869.0,
    "verified": false,
    "location": "\u0627\u0644\u0644\u0647 \u0623\u0643\u0628\u0631"
  },
  "1373252581330448387": {
    "username": "sharktatoe",
    "liked": [
      1490228075933671429
    ],
    "created_at": 1616243916.0,
    "verified": false,
    "location": "Twitter."
  },
  "362930212": {
    "username": "fengvictoria",
    "liked": [
      1490321706833035267
    ],
    "created_at": 1314427433.0,
    "verified": false,
    "location": "Anti-war, Anti-racism; Canada"
  },
  "887086072710275072": {
    "username": "TANK_PILLED",
    "liked": [
      1490321706833035267
    ],
    "created_at": 1500332775.0,
    "verified": false
  },
  "1342920095413260289": {
    "username": "Alexand85266011",
    "liked": [
      1490323343177830407
    ],
    "created_at": 1609012107.0,
    "verified": false,
    "location": "United Kingdom"
  },
  "775752530684936196": {
    "username": "Politicalpete55",
    "liked": [
      1490323343177830407
    ],
    "created_at": 1473788791.0,
    "verified": false,
    "location": "Central Belt"
  },
  "1213215634047172608": {
    "username": "McsHelen",
    "liked": [
      1490323343177830407
    ],
    "created_at": 1578088184.0,
    "verified": false,
    "location": "Scotland"
  },
  "1434078265816272900": {
    "username": "dallro1",
    "liked": [
      1490323343177830407
    ],
    "created_at": 1630745903.0,
    "verified": false
  },
  "1374035424826556421": {
    "username": "CountMertola",
    "liked": [
      1490323343177830407
    ],
    "created_at": 1616430595.0,
    "verified": false,
    "location": "West Lothian "
  },
  "573867961": {
    "username": "Tighfiodh",
    "liked": [
      1490323343177830407
    ],
    "created_at": 1336415637.0,
    "verified": false,
    "location": "West Highlands "
  },
  "4776306661": {
    "username": "DebbietymJams",
    "retweeted": [
      1490339257541562368
    ],
    "created_at": 1453083601.0,
    "verified": false,
    "location": "Saskatoon, Saskatchewan",
    "liked": [
      1490339257541562368
    ]
  },
  "1225825524074897409": {
    "username": "sr_seymore",
    "liked": [
      1490339257541562368
    ],
    "created_at": 1581094586.0,
    "verified": false,
    "location": "Minnesota, USA"
  },
  "359074674": {
    "username": "NewDayStarts",
    "retweeted": [
      1490347199875715086
    ],
    "created_at": 1313885582.0,
    "verified": false,
    "location": "Lowestoft - England",
    "liked": [
      1490347199875715086
    ]
  },
  "1606070449": {
    "username": "originprojects",
    "liked": [
      1490347199875715086
    ],
    "created_at": 1374243962.0,
    "verified": false,
    "location": "UK Wide"
  },
  "461645476": {
    "username": "marksonofwil",
    "liked": [
      1490347199875715086
    ],
    "created_at": 1326331006.0,
    "verified": false,
    "location": "United Kingdom"
  },
  "1144274884715061248": {
    "username": "fae_support",
    "liked": [
      1490347199875715086
    ],
    "created_at": 1561651366.0,
    "verified": false,
    "location": "United Kingdom"
  },
  "1201329681234104320": {
    "username": "Wecantgiveupeva",
    "retweeted": [
      1490380158632669185
    ],
    "created_at": 1575254307.0,
    "verified": false,
    "location": "Florida, USA",
    "liked": [
      1490380158632669185
    ]
  },
  "46052927": {
    "username": "SeanBlack07",
    "liked": [
      1490380158632669185
    ],
    "created_at": 1244615122.0,
    "verified": false,
    "location": "United States"
  },
  "1260998413": {
    "username": "cydney432",
    "liked": [
      1490380158632669185
    ],
    "created_at": 1363058388.0,
    "verified": false,
    "location": "learning something new or old "
  },
  "2166957823": {
    "username": "Chewyweeks",
    "liked": [
      1490380158632669185
    ],
    "created_at": 1383239936.0,
    "verified": false
  },
  "1293290846163533832": {
    "username": "kelvin45622",
    "liked": [
      1490380158632669185
    ],
    "created_at": 1597179593.0,
    "verified": false,
    "location": "coon free state"
  },
  "984162493332426753": {
    "username": "skandyn_",
    "liked": [
      1490433842469122050
    ],
    "created_at": 1523477598.0,
    "verified": false,
    "location": "\u0555\u0584\u057d\u056b\u057f\u0561\u0576\u056b\u0561 "
  },
  "1318145110585036802": {
    "username": "beglaryan_davit",
    "liked": [
      1490433842469122050
    ],
    "created_at": 1603105266.0,
    "verified": false,
    "location": "Armenia, Yerevan"
  },
  "1249938966012465152": {
    "username": "VirionSolz",
    "liked": [
      1490502481452875777
    ],
    "created_at": 1586843663.0,
    "verified": false,
    "location": "jrwitwt + counciltwt"
  },
  "1184462481076473857": {
    "username": "DelliciousPaul1",
    "liked": [
      1490592866929979399
    ],
    "created_at": 1571232864.0,
    "verified": false
  },
  "1662036991": {
    "username": "saudamini88",
    "liked": [
      1490620880233197570
    ],
    "created_at": 1376209632.0,
    "verified": false,
    "location": "Nowhere"
  },
  "3023773069": {
    "username": "Rake4169Rakesh",
    "liked": [
      1490689187007324161
    ],
    "created_at": 1424171033.0,
    "verified": false
  },
  "1217480915879809030": {
    "username": "Ayush7055",
    "liked": [
      1490689187007324161
    ],
    "created_at": 1579105055.0,
    "verified": false,
    "location": "Aligarh, India"
  },
  "1525992979": {
    "username": "SuzikiSevgi",
    "retweeted": [
      1491046333536665604
    ],
    "created_at": 1371505648.0,
    "verified": false
  },
  "1281397862685966341": {
    "username": "LeiaBryant13",
    "retweeted": [
      1491046333536665604
    ],
    "created_at": 1594344052.0,
    "verified": false,
    "location": "\u26e4chaotic good\u26e48w7\u26e4INFP"
  },
  "314700035": {
    "username": "DrJessTaylor",
    "retweeted": [
      1491046333536665604
    ],
    "created_at": 1307726942.0,
    "verified": true,
    "location": "England, United Kingdom"
  },
  "1025539736": {
    "username": "hekataia",
    "liked": [
      1491046333536665604
    ],
    "created_at": 1356059750.0,
    "verified": false
  },
  "706958383472099329": {
    "username": "EssyD_",
    "liked": [
      1491046333536665604
    ],
    "created_at": 1457386988.0,
    "verified": false,
    "location": "London "
  },
  "1401673830523883521": {
    "username": "Maxie18537862",
    "liked": [
      1491046333536665604
    ],
    "created_at": 1623020107.0,
    "verified": false
  },
  "391252953": {
    "username": "LostinLauzerte",
    "liked": [
      1491046333536665604
    ],
    "created_at": 1318668523.0,
    "verified": false,
    "location": "France"
  },
  "2619503069": {
    "username": "sjwr_i",
    "liked": [
      1491046333536665604
    ],
    "created_at": 1403080587.0,
    "verified": false
  },
  "34895884": {
    "username": "mini_ftw",
    "liked": [
      1491046333536665604
    ],
    "created_at": 1240569610.0,
    "verified": false,
    "location": "\u2728Terf Island\u2728"
  },
  "69906733": {
    "username": "Mid_LifeBassist",
    "liked": [
      1491046333536665604
    ],
    "created_at": 1251564250.0,
    "verified": false,
    "location": "Italy & Scotland"
  },
  "1208688338": {
    "username": "limpet67",
    "liked": [
      1491046333536665604
    ],
    "created_at": 1361542799.0,
    "verified": false,
    "location": "Glasgow, Scotland"
  },
  "944584045": {
    "username": "NuriaCruzCruz",
    "liked": [
      1491046333536665604
    ],
    "created_at": 1352753899.0,
    "verified": false
  },
  "60509993": {
    "username": "TalesOfColor",
    "liked": [
      1491046333536665604
    ],
    "created_at": 1248675592.0,
    "verified": false
  },
  "757389727276404736": {
    "username": "NNdwandweLegacy",
    "retweeted": [
      1491054588815978501
    ],
    "created_at": 1469410757.0,
    "verified": false,
    "location": "South Africa",
    "liked": [
      1491054588815978501
    ]
  },
  "946147878522839040": {
    "username": "Free_Sanitary_P",
    "retweeted": [
      1491054588815978501
    ],
    "created_at": 1514414207.0,
    "verified": false,
    "location": "South Africa / Global",
    "liked": [
      1491054588815978501
    ]
  },
  "3052837660": {
    "username": "cathyvitaliano",
    "retweeted": [
      1491054588815978501
    ],
    "created_at": 1424615489.0,
    "verified": false,
    "location": " \ud83c\uddf8\ud83c\uddf8 ",
    "liked": [
      1491054588815978501
    ]
  },
  "2248865157": {
    "username": "Nokuzola_SA",
    "retweeted": [
      1491054588815978501
    ],
    "created_at": 1388266982.0,
    "verified": false,
    "location": "Global Citizen \u2b55\ufe0f",
    "liked": [
      1491054588815978501
    ]
  },
  "2188703611": {
    "username": "TexAlbert",
    "liked": [
      1491054588815978501
    ],
    "created_at": 1384188921.0,
    "verified": false,
    "location": "Laval, Qu\u00e9bec"
  },
  "1447603995179057156": {
    "username": "divestfossils",
    "liked": [
      1491057486324895744
    ],
    "created_at": 1633970670.0,
    "verified": false
  },
  "1431729555182600197": {
    "username": "Heggs_HHiF",
    "liked": [
      1491114654210596865
    ],
    "created_at": 1630185951.0,
    "verified": false,
    "location": "MF'n 610"
  },
  "302318309": {
    "username": "SidiSasa",
    "liked": [
      1491154978186145802
    ],
    "created_at": 1305936721.0,
    "verified": false,
    "location": "Grand Hotel BANFORA BF"
  },
  "876838253801897984": {
    "username": "LeandriClaire",
    "liked": [
      1491154978186145802
    ],
    "created_at": 1497889505.0,
    "verified": false
  },
  "943913254321041408": {
    "username": "sarnchos",
    "retweeted": [
      1491318816491675649
    ],
    "created_at": 1513881431.0,
    "verified": false,
    "location": "Owo, Nigeria"
  },
  "1154794876510396419": {
    "username": "endsarsbot_",
    "retweeted": [
      1491318816491675649
    ],
    "created_at": 1564159528.0,
    "verified": false,
    "location": "World"
  },
  "2817199388": {
    "username": "TtifeB",
    "liked": [
      1491318816491675649
    ],
    "created_at": 1411053582.0,
    "verified": false
  },
  "1033009779797618688": {
    "username": "abob_f",
    "liked": [
      1491318816491675649
    ],
    "created_at": 1535123698.0,
    "verified": false,
    "location": "Lagos, Nigeria"
  },
  "144607874": {
    "username": "Olumupa",
    "liked": [
      1491318816491675649
    ],
    "created_at": 1274040756.0,
    "verified": false,
    "location": "Rogers, MN"
  },
  "28532939": {
    "username": "ustyn",
    "liked": [
      1491318816491675649
    ],
    "created_at": 1238751175.0,
    "verified": false,
    "location": "Abuja, Nigeria"
  },
  "220776068": {
    "username": "vicktop55",
    "liked": [
      1491392699429101573
    ],
    "created_at": 1290974911.0,
    "verified": false,
    "location": "Russia "
  },
  "1275181260256743426": {
    "username": "EmekaPhilip11",
    "retweeted": [
      1491439588745035778
    ],
    "created_at": 1592861895.0,
    "verified": false
  },
  "713514945401499648": {
    "username": "BabaAwai",
    "liked": [
      1491476570539802628
    ],
    "created_at": 1458950194.0,
    "verified": false
  },
  "351483701": {
    "username": "madasawetwasp",
    "retweeted": [
      1491490702383095811
    ],
    "created_at": 1312882017.0,
    "verified": false,
    "location": "Leigh on Sea"
  },
  "1484905433147985920": {
    "username": "Alzaabi71AD",
    "retweeted": [
      1491723108113436672
    ],
    "created_at": 1642864030.0,
    "verified": false,
    "liked": [
      1491723108113436672
    ]
  },
  "2565294852": {
    "username": "Nassimejonub",
    "liked": [
      1491723108113436672
    ],
    "created_at": 1402665991.0,
    "verified": false,
    "location": "Berlin, Germany"
  },
  "1035172426093654017": {
    "username": "alt_ali9",
    "liked": [
      1491723108113436672
    ],
    "created_at": 1535639313.0,
    "verified": false
  },
  "2264722771": {
    "username": "AathmaTheSoul",
    "liked": [
      1491723108113436672
    ],
    "created_at": 1388167462.0,
    "verified": false,
    "location": "Saturn \ud83e\ude90"
  },
  "1375140751777103874": {
    "username": "pammyINdiana",
    "liked": [
      1491935368014405632
    ],
    "created_at": 1616694139.0,
    "verified": false,
    "location": "Somewhere in the middle, USA "
  },
  "869004296": {
    "username": "judigorgacz",
    "liked": [
      1491935368014405632
    ],
    "created_at": 1349746048.0,
    "verified": false
  },
  "1298263416017022981": {
    "username": "Julia48395848",
    "liked": [
      1492115993724096512
    ],
    "created_at": 1598365112.0,
    "verified": false
  },
  "3063486958": {
    "username": "catqueen93",
    "liked": [
      1492121901619048450
    ],
    "created_at": 1424900112.0,
    "verified": false,
    "location": "Tampa, FL"
  },
  "2415964091": {
    "username": "SlimanGaming",
    "retweeted": [
      1492165655654813700
    ],
    "created_at": 1394999397.0,
    "verified": false,
    "location": "Canada",
    "liked": [
      1492165655654813700
    ]
  },
  "1267715753043623937": {
    "username": "samuel_kemble",
    "liked": [
      1492166639638532098
    ],
    "created_at": 1591081981.0,
    "verified": false,
    "location": "Edmonton, Alberta, Canada"
  },
  "1431258142772371460": {
    "username": "Jreatsdung",
    "liked": [
      1492241223851118599
    ],
    "created_at": 1630073560.0,
    "verified": false,
    "location": "Like Hoth but more local. "
  },
  "1243769891326328833": {
    "username": "usagyaaru",
    "liked": [
      1492259756651732993
    ],
    "created_at": 1585372849.0,
    "verified": false,
    "location": "! read carrd byf please !"
  },
  "829530862907752451": {
    "username": "Anya20012007",
    "retweeted": [
      1492275130340413441
    ],
    "created_at": 1486610544.0,
    "verified": false,
    "liked": [
      1492275130340413441
    ]
  },
  "1876822015": {
    "username": "Pastor_LeClara1",
    "retweeted": [
      1492275130340413441
    ],
    "created_at": 1379449343.0,
    "verified": false,
    "location": "Atlanta, GA",
    "liked": [
      1492275130340413441
    ]
  },
  "65437231": {
    "username": "HumanBiotics",
    "retweeted": [
      1492275130340413441
    ],
    "created_at": 1250189781.0,
    "verified": false,
    "location": "Sao Paulo, Brazi",
    "liked": [
      1492275130340413441
    ]
  },
  "1137493770407239681": {
    "username": "horta_chico",
    "retweeted": [
      1492275130340413441
    ],
    "created_at": 1560034623.0,
    "verified": false
  },
  "210124287": {
    "username": "daniescott3000",
    "retweeted": [
      1492275130340413441
    ],
    "created_at": 1288456989.0,
    "verified": false,
    "location": "Brooklyn, NY"
  },
  "313587957": {
    "username": "Mike_Lowrey5",
    "retweeted": [
      1492275130340413441
    ],
    "created_at": 1307570688.0,
    "verified": false,
    "location": "Out The Way"
  },
  "2480393435": {
    "username": "knobetter",
    "retweeted": [
      1492275130340413441
    ],
    "created_at": 1397356691.0,
    "verified": false,
    "location": "Atlanta, GA"
  },
  "1320783320754593792": {
    "username": "TheCirc92826597",
    "retweeted": [
      1492275130340413441
    ],
    "created_at": 1603734356.0,
    "verified": false
  },
  "1292133497621053441": {
    "username": "cpc_yes",
    "retweeted": [
      1492275130340413441
    ],
    "created_at": 1596903615.0,
    "verified": false,
    "location": "Boston, MA"
  },
  "52415376": {
    "username": "pez1963",
    "retweeted": [
      1492275130340413441
    ],
    "created_at": 1246373695.0,
    "verified": false,
    "location": "Nashville TN "
  },
  "826414119096025088": {
    "username": "yippeekiyaymfs",
    "retweeted": [
      1492275130340413441
    ],
    "created_at": 1485867454.0,
    "verified": false
  },
  "603094930": {
    "username": "reypoullard",
    "retweeted": [
      1492275130340413441
    ],
    "created_at": 1339192256.0,
    "verified": false,
    "location": "Proof-Of-Work (PoW)  \u27a0  SOON"
  },
  "1190009851285520385": {
    "username": "JackEntot",
    "retweeted": [
      1492275130340413441
    ],
    "created_at": 1572555442.0,
    "verified": false
  },
  "1267196427903606785": {
    "username": "sayWORD93",
    "retweeted": [
      1492275130340413441
    ],
    "created_at": 1590958166.0,
    "verified": false,
    "location": "Uptown"
  },
  "149480754": {
    "username": "PtahMyoo",
    "retweeted": [
      1492275130340413441
    ],
    "created_at": 1275133636.0,
    "verified": false,
    "location": "The Cave"
  },
  "986355928512507904": {
    "username": "Trenee03283254",
    "liked": [
      1492275130340413441
    ],
    "created_at": 1524000553.0,
    "verified": false
  },
  "222123017": {
    "username": "Luv2h8blee",
    "liked": [
      1492275130340413441
    ],
    "created_at": 1291300883.0,
    "verified": false,
    "location": "Charlottesville VA"
  },
  "627920699": {
    "username": "Showcasemyblog1",
    "liked": [
      1492275130340413441
    ],
    "created_at": 1341538508.0,
    "verified": false,
    "location": "Columbia, SC"
  },
  "251283024": {
    "username": "maliksmoma",
    "liked": [
      1492275130340413441
    ],
    "created_at": 1297542782.0,
    "verified": false,
    "location": "Texas, USA"
  },
  "846040703864066052": {
    "username": "NathanRollins14",
    "liked": [
      1492275130340413441
    ],
    "created_at": 1490546797.0,
    "verified": false
  },
  "1327409740826120192": {
    "username": "scooter38th",
    "liked": [
      1492275130340413441
    ],
    "created_at": 1605314148.0,
    "verified": false
  },
  "977011440434499584": {
    "username": "OMA_Project",
    "liked": [
      1492275130340413441
    ],
    "created_at": 1521772654.0,
    "verified": false,
    "location": "CT"
  },
  "1166195858746019840": {
    "username": "OptimusSun112",
    "liked": [
      1492275130340413441
    ],
    "created_at": 1566877752.0,
    "verified": false
  },
  "2556343792": {
    "username": "IronMaiden617",
    "liked": [
      1492275130340413441
    ],
    "created_at": 1400631983.0,
    "verified": false,
    "location": "6th Level of Purgatory"
  },
  "1045520113150001152": {
    "username": "TFredette2",
    "liked": [
      1492275130340413441
    ],
    "created_at": 1538106394.0,
    "verified": false
  },
  "801302241961537536": {
    "username": "jah_son_IAM",
    "liked": [
      1492275130340413441
    ],
    "created_at": 1479880316.0,
    "verified": false
  },
  "1129650026060406784": {
    "username": "DariusHackworth",
    "liked": [
      1492275130340413441
    ],
    "created_at": 1558164528.0,
    "verified": false
  },
  "1453514465949925376": {
    "username": "ObinsoOnuoha",
    "retweeted": [
      1492335184988958723
    ],
    "created_at": 1635379861.0,
    "verified": false,
    "location": "Biafra"
  },
  "1351678818117939205": {
    "username": "OscarIwunze",
    "retweeted": [
      1492335184988958723
    ],
    "created_at": 1611100341.0,
    "verified": false,
    "liked": [
      1492335184988958723
    ]
  },
  "1480065760382832640": {
    "username": "maxikenechukwu",
    "retweeted": [
      1492335184988958723
    ],
    "created_at": 1641710209.0,
    "verified": false,
    "location": "Regno Unito"
  },
  "1253640868340391938": {
    "username": "JoakeemK",
    "retweeted": [
      1492335184988958723
    ],
    "created_at": 1587726288.0,
    "verified": false,
    "location": "Heaven \ud83c\uddf3\ud83c\uddf4 Nodsk"
  },
  "1353314552876822529": {
    "username": "stancross50",
    "retweeted": [
      1492335184988958723
    ],
    "created_at": 1611490342.0,
    "verified": false
  },
  "1290996104084033536": {
    "username": "GoldenBalance86",
    "retweeted": [
      1492335184988958723
    ],
    "created_at": 1596632482.0,
    "verified": false,
    "location": "Captivity until Biafra comes",
    "liked": [
      1492335184988958723
    ]
  },
  "1242688084178694144": {
    "username": "McintoshTracker",
    "liked": [
      1492430725161054208
    ],
    "created_at": 1585114955.0,
    "verified": false
  },
  "897258090210504704": {
    "username": "NathalieDenis17",
    "liked": [
      1492430725161054208
    ],
    "created_at": 1502757973.0,
    "verified": false
  },
  "405113404": {
    "username": "adam_christ_boy",
    "liked": [
      1492430725161054208
    ],
    "created_at": 1320442996.0,
    "verified": false,
    "location": "End of the bar"
  },
  "1391174779986657281": {
    "username": "nibs56139211",
    "liked": [
      1492430725161054208
    ],
    "created_at": 1620516950.0,
    "verified": false,
    "location": "Canada"
  },
  "200692199": {
    "username": "Helen_V_Leggatt",
    "liked": [
      1492430725161054208
    ],
    "created_at": 1286669557.0,
    "verified": false,
    "location": "Canterbury Region, New Zealand"
  },
  "297813399": {
    "username": "JoChiaradia",
    "retweeted": [
      1492565296682455041
    ],
    "created_at": 1305262235.0,
    "verified": false,
    "location": "       ",
    "liked": [
      1492565296682455041
    ]
  },
  "1281692883607748608": {
    "username": "BARBARA55024190",
    "liked": [
      1492565296682455041
    ],
    "created_at": 1594414427.0,
    "verified": false
  },
  "1396603352": {
    "username": "AussieNRLMum",
    "liked": [
      1492565296682455041
    ],
    "created_at": 1367482914.0,
    "verified": false,
    "location": "Australia"
  },
  "1085918253074055168": {
    "username": "PremiershipL",
    "liked": [
      1492570047583334412
    ],
    "created_at": 1547738061.0,
    "verified": false,
    "location": "Channelling Positivity"
  },
  "2683966702": {
    "username": "LayeredStrange",
    "liked": [
      1492570047583334412
    ],
    "created_at": 1404753093.0,
    "verified": false,
    "location": "Doncaster, England"
  },
  "1441305366046801923": {
    "username": "Cullum3Cullum",
    "liked": [
      1492570047583334412
    ],
    "created_at": 1632468985.0,
    "verified": false
  },
  "915976762911334401": {
    "username": "Matthewwilding7",
    "liked": [
      1492570047583334412
    ],
    "created_at": 1507220853.0,
    "verified": false
  },
  "1060349531370463234": {
    "username": "baratheongirl",
    "liked": [
      1492570047583334412
    ],
    "created_at": 1541642003.0,
    "verified": false,
    "location": "Ogmore, Cymru"
  },
  "708694626333495296": {
    "username": "jouhaan_",
    "liked": [
      1492570047583334412
    ],
    "created_at": 1457800940.0,
    "verified": false,
    "location": "Brexit Plague Island"
  },
  "1551824163580612609": {
    "username": "TeaJay6731263",
    "liked": [
      1492571556849070085
    ],
    "created_at": 1658818728.0,
    "verified": false
  },
  "1253816613159256068": {
    "username": "Bomb_suit_guy",
    "liked": [
      1492571556849070085
    ],
    "created_at": 1587768257.0,
    "verified": false,
    "location": "On your trail cam"
  },
  "924983608829530113": {
    "username": "CorwinianW",
    "liked": [
      1492571556849070085
    ],
    "created_at": 1509368252.0,
    "verified": false,
    "location": "To close too DC"
  },
  "1294356367222943744": {
    "username": "WildinYourJimmi",
    "liked": [
      1492571556849070085
    ],
    "created_at": 1597433604.0,
    "verified": false,
    "location": "\ud835\udd7e\ud835\udd7e \ud835\udd7d\ud835\udd94\ud835\udd98\ud835\udd8a | They/Them"
  },
  "1280259968730628099": {
    "username": "rudyceballos7",
    "liked": [
      1492605761213673472
    ],
    "created_at": 1594072818.0,
    "verified": false,
    "location": "Langley, Virginia "
  },
  "322699008": {
    "username": "BryanDBender",
    "liked": [
      1492605761213673472
    ],
    "created_at": 1308845395.0,
    "verified": true,
    "location": "Washington and Phoenix"
  },
  "728248668147560450": {
    "username": "ChristinePapuga",
    "retweeted": [
      1492623487222964224
    ],
    "created_at": 1462462987.0,
    "verified": false,
    "location": "Missouri, USA",
    "liked": [
      1492623487222964224
    ]
  },
  "1487536827913445378": {
    "username": "KiersteadSally",
    "liked": [
      1492623487222964224
    ],
    "created_at": 1643491406.0,
    "verified": false
  },
  "971123887407796225": {
    "username": "Standupchai",
    "liked": [
      1492623487222964224
    ],
    "created_at": 1520368952.0,
    "verified": false,
    "location": "SharpieGate Zone, Alabama, USA"
  },
  "860380399712784385": {
    "username": "CrispinJPorter",
    "liked": [
      1492623487222964224
    ],
    "created_at": 1493965647.0,
    "verified": false,
    "location": "EARTH"
  },
  "1363325062112157697": {
    "username": "peggy_roane",
    "liked": [
      1492623487222964224
    ],
    "created_at": 1613877014.0,
    "verified": false
  },
  "1311130157311299591": {
    "username": "jac314stl",
    "liked": [
      1492623487222964224
    ],
    "created_at": 1601432837.0,
    "verified": false
  },
  "938243294": {
    "username": "razeyourfist",
    "liked": [
      1492623487222964224
    ],
    "created_at": 1352515484.0,
    "verified": false,
    "location": "somewhere, small town USA "
  },
  "837948372": {
    "username": "gunderwood3",
    "liked": [
      1492623487222964224
    ],
    "created_at": 1348238975.0,
    "verified": false
  },
  "1080279026340483073": {
    "username": "Anitasaidthis",
    "liked": [
      1492623487222964224
    ],
    "created_at": 1546393565.0,
    "verified": false,
    "location": "United States"
  },
  "3010662156": {
    "username": "LucyCoppes",
    "liked": [
      1492623487222964224
    ],
    "created_at": 1423186621.0,
    "verified": false
  },
  "346192325": {
    "username": "ninesteps2",
    "liked": [
      1492623487222964224
    ],
    "created_at": 1312148844.0,
    "verified": false
  },
  "705407169428992000": {
    "username": "PatiWoman7",
    "liked": [
      1492623487222964224
    ],
    "created_at": 1457017149.0,
    "verified": false,
    "location": "Pennsylvania, USA"
  },
  "1487477560124530689": {
    "username": "Vanessablue6011",
    "liked": [
      1492623487222964224
    ],
    "created_at": 1643477308.0,
    "verified": false
  },
  "278959439": {
    "username": "Ara_Kahu",
    "liked": [
      1492656691074113538
    ],
    "created_at": 1302254584.0,
    "verified": false,
    "location": "Aotearoa-New Zealand"
  },
  "2797948887": {
    "username": "BehavEcolPapers",
    "retweeted": [
      1492794959950352387
    ],
    "created_at": 1412169720.0,
    "verified": false,
    "location": "global"
  },
  "825644121448669184": {
    "username": "BlayneyDeborah",
    "liked": [
      1492806887393406978
    ],
    "created_at": 1485683873.0,
    "verified": false
  },
  "2723916877": {
    "username": "Blossom_Ferns",
    "liked": [
      1492810896531652609
    ],
    "created_at": 1407761347.0,
    "verified": false,
    "location": "India"
  },
  "800885710614130688": {
    "username": "pikaboss89",
    "liked": [
      1492899568974979082
    ],
    "created_at": 1479781007.0,
    "verified": false
  },
  "1128113520237776897": {
    "username": "Tjlee110",
    "liked": [
      1492899568974979082
    ],
    "created_at": 1557798197.0,
    "verified": false
  },
  "1386754489370124289": {
    "username": "T3CHNOSC4RL3T",
    "liked": [
      1492899568974979082
    ],
    "created_at": 1619463020.0,
    "verified": false,
    "location": "I spam rt technofanart beware"
  }
}